[
    {
    "id": 10,
    "product": "QVD Viewer",
    "files": 
        [
            {
                "type": "app",
                "file name": "ODAG-Selection-app",
                "version": "1.0.0",
                "source": "https://github.com/bitmetric-bv/bitmetric-qvd-viewer/raw/main/content/ODAG-Selection-app.qvf",
                "bitmetric-installer" : true
            },
            {
                "type": "app",
                "file name": "ODAG-Data-profiling-app",
                "version": "1.0.0",
                "source": "https://github.com/bitmetric-bv/bitmetric-qvd-viewer/raw/main/content/ODAG-Data-profiling-app.qvf",
                "bitmetric-installer" : true
            },
            {
                "type": "automation",
                "file name": "ODAG-App-Reload",
                "version": "1.0.0",
                "source": "https://github.com/bitmetric-bv/bitmetric-qvd-viewer/raw/main/content/ODAG-App-Reload.json",
                "bitmetric-installer" : true
            }
        ],
    "input":"The installer for the QVD Viewer first verifies the required conditions before the actual installation can begin.\n\nIf all conditions are met, the process will continue by installing the automation ODAG-App-Reload.\n\nAfter that, the installer will deploy the following applications:\n- ODAG-Selection-App\n- ODAG-Data-Profiling-App\n\nDuring installation, the process will check if a previous version already exists. If so, the user will be asked whether the existing version should be removed before proceeding.",
    "output":"### Last Steps for you:\n\nWe need your help for the last steps. You need to synchronize the button with the automation to get the right Execution Token.\n\n#### Step 1:\nOpen [ODAG Selection App](https://bitmetric-bv.eu.qlikcloud.com/sense/app/{$.oSettings.ODAG-Selection-app})\n*Tip: Press CTRL to open in new tab*\n\n#### Step 2:\nEdit the master-item: **Reload button** and link this to the new automation: **ODAG App Reload**.\n\n#### Step 3:\nSetup **ODAG connection**. To explain.\n\n#### Step 4:\nStart enjoying your QVD Cloud Viewer! ☀\n\nRegards,\nYour friends at [**Bitmetric**](https://www.bitmetric.nl)\n\n💌 Need help? Contact us at [support@bitmetric.nl](mailto:support@bitmetric.nl)",
    "tag name": ["QVD-Viewer", "Bitmetric"],
    "api-key_required": false,
    "data-connection": false,
    "tenant-admin":true
    },
    {
    "id": 20,
    "product": "Master Item Viewer",
    "files": 
        [
            {
                "type": "app",
                "file name": "Tenant-extract-app",
                "version": "1.0.0",
                "source": "https://github.com/bitmetric-bv/bitmetric-qvd-viewer/raw/main/content/Tenant-extract-app.qvf",
                "bitmetric-installer" : true
            },
            {
                "type": "app",
                "file name": "Master-item-app",
                "version": "1.0.0",
                "source": "https://github.com/bitmetric-bv/bitmetric-qvd-viewer/raw/main/content/Master-item-app.qvf",
                "bitmetric-installer" : true
            },
            {
                "type": "automation",
                "file name": "Master-measure-automation",
                "version": "1.0.0",
                "source": "https://github.com/bitmetric-bv/bitmetric-qvd-viewer/raw/main/content/Master-measure-automation.json",
                "bitmetric-installer" : true,
                "save_id_in" : "bitmetric_id_1"
            },
            {
                "type": "automation",
                "file name": "Master-dimension-automation",
                "version": "1.0.0",
                "source": "https://github.com/bitmetric-bv/bitmetric-qvd-viewer/raw/main/content/Master-dimension-automationjson",
                "bitmetric-installer" : true,
                "save_id_in" : "bitmetric_id_2"
            }
        ],
    "input":"Input master item",
    "output":"output master item",
    "tag name": ["Master-item-viewer", "Bitmetric"],
    "api-key_required": true,
    "data-connection": true,
    "tenant-admin":true
    
    }
]
